xesmf/__init__.py
xesmf/_version.py
xesmf/backend.py
xesmf/data.py
xesmf/frontend.py
xesmf/smm.py
xesmf/util.py
xesmf/tests/__init__.py
xesmf/tests/conftest.py
xesmf/tests/test_backend.py
xesmf/tests/test_frontend.py
xesmf/tests/test_oceanmodels.py
xesmf/tests/test_smm.py
xesmf/tests/test_util.py
pangeo_xesmf-0.7.0.post0.dist-info/LICENSE
pangeo_xesmf-0.7.0.post0.dist-info/METADATA
pangeo_xesmf-0.7.0.post0.dist-info/WHEEL
pangeo_xesmf-0.7.0.post0.dist-info/top_level.txt
pangeo_xesmf-0.7.0.post0.dist-info/RECORD
