Metadata-Version: 2.1
Name: pangeo-xesmf
Version: 0.7.0.post0
Summary: Universal Regridder for Geospatial Data
Home-page: https://github.com/pangeo-data/xESMF
Author: Jiawei Zhuang
Author-email: jiaweizhuang@g.harvard.edu
License: MIT
Classifier: Development Status :: 4 - Beta
Classifier: License :: OSI Approved :: MIT License
Classifier: Operating System :: OS Independent
Classifier: Intended Audience :: Science/Research
Classifier: Programming Language :: Python
Classifier: Programming Language :: Python :: 3
Classifier: Programming Language :: Python :: 3.6
Classifier: Programming Language :: Python :: 3.7
Classifier: Programming Language :: Python :: 3.8
Classifier: Topic :: Scientific/Engineering
Requires-Python: >=3.6
License-File: LICENSE
Requires-Dist: esmpy
Requires-Dist: xarray (>=0.16.2)
Requires-Dist: numpy (>=1.16)
Requires-Dist: shapely (<2.0)
Requires-Dist: cf-xarray (>=0.5.1)
Requires-Dist: sparse (>=0.8.0)
Requires-Dist: numba (>=0.55.2)
